mark1_translate/__init__.py
mark1_translate/mark1.py
mark1_translate-0.1.7.dist-info/LICENSE
mark1_translate-0.1.7.dist-info/WHEEL
mark1_translate-0.1.7.dist-info/METADATA
mark1_translate-0.1.7.dist-info/RECORD
