Metadata-Version: 2.1
Name: mark1-translate
Version: 0.1.7
Summary: Google Translate based api
Home-page: https://github.com/cgmark101/mark1-translate
License: MIT
Author: cgmark101
Author-email: cgmark101@gmail.com
Requires-Python: >=3.8,<4.0
Classifier: License :: OSI Approved :: MIT License
Classifier: Programming Language :: Python :: 3
Classifier: Programming Language :: Python :: 3.8
Classifier: Programming Language :: Python :: 3.9
Requires-Dist: requests (>=2.26.0,<3.0.0)
Project-URL: Repository, https://github.com/cgmark101/mark1-translate
